{
    "fileServerStatus": "started",
    "dataClient": {
        "type": "Vicon",
        "SDK": "C:/Program Files/Vicon/DataStream SDK/Win64/dotNET/ViconDataStreamSDK_DotNET.dll",
        "url": "localhost",
        "port": 801,
        "pollInterval": 20,
        "pollType": "pull"
    },
    "labVIEWComm": {
        "port": 6123
    },
    "side": "R",
    "mkrsLoc": {
        "mT2": {
            "pos": [
                -57.0325,
                -273.8666,
                140.4072
            ]
        },
        "mT3": {
            "pos": [
                -67.5248,
                -258.2357,
                47.2126
            ]
        },
        "mT1": {
            "pos": [
                -120.9411,
                -251.9802,
                99.2294
            ]
        },
        "FHC": {
            "pos": [
                9.4268,
                -51.8592,
                612.4303
            ]
        },
        "FLE": {
            "pos": [
                -23.0305,
                -124.187,
                260.1826
            ]
        },
        "TKC": {
            "pos": [
                9.1822,
                -107.9099,
                235.3582
            ]
        },
        "mF1": {
            "pos": [
                -115.9645,
                -227.2391,
                402.2707
            ]
        },
        "mF2": {
            "pos": [
                -59.6494,
                -225.3782,
                454.903
            ]
        },
        "mF3": {
            "pos": [
                -43.4073,
                -238.7613,
                363.7633
            ]
        },
        "mF4": {
            "pos": [
                -132.6541,
                -141.7251,
                395.9014
            ]
        },
        "TAC": {
            "pos": [
                -11.3669,
                -98.5209,
                -83.7967
            ]
        },
        "FKC": {
            "pos": [
                14.2298,
                -122.0387,
                243.425
            ]
        },
        "TPM": {
            "pos": [
                42.9124,
                -103.5753,
                228.0779
            ]
        },
        "TPL": {
            "pos": [
                -21.1375,
                -117.6308,
                231.9782
            ]
        },
        "FLCC": {
            "pos": [
                -10.3974,
                -115.8444,
                253.4443
            ]
        },
        "FMCL": {
            "pos": [
                49.2056,
                -103.7274,
                256.3688
            ]
        },
        "mT4": {
            "pos": [
                -118.6083,
                -161.4379,
                104.0218
            ]
        },
        "FME": {
            "pos": [
                50.0912,
                -106.5834,
                254.795
            ]
        },
        "FMCC": {
            "pos": [
                29.3966,
                -99.3751,
                249.6612
            ]
        },
        "TMCP": {
            "pos": [
                21.8245,
                -87.9204,
                228.7193
            ]
        },
        "TLCP": {
            "pos": [
                -14.0062,
                -99.67,
                228.9098
            ]
        },
        "TMCA": {
            "pos": [
                32.084,
                -127.855,
                232.2631
            ]
        },
        "TMCC": {
            "pos": [
                25.739,
                -107.0144,
                231.3183
            ]
        },
        "TMCL": {
            "pos": [
                21.1704,
                -108.4569,
                176.2609
            ]
        },
        "TLCA": {
            "pos": [
                -5.0069,
                -131.4017,
                230.4314
            ]
        },
        "TLCC": {
            "pos": [
                -8.0572,
                -114.0371,
                231.8557
            ]
        }
    },
    "splines": {
        "TibiaPlateauMedEdge": {
            "pos": [
                [
                    18.59,
                    -136.96,
                    228
                ],
                [
                    31.18,
                    -132.54,
                    228
                ],
                [
                    38.81,
                    -124.67,
                    228
                ],
                [
                    41.63,
                    -119.15,
                    228
                ],
                [
                    44.25,
                    -105.07,
                    228
                ],
                [
                    37.98,
                    -90.91,
                    227.34
                ],
                [
                    20.93,
                    -87.34,
                    228
                ]
            ]
        }
    },
    "wand": {
        "type": "KneeRigStylus",
        "markersToUse": [
            "WN",
            "WW",
            "WE",
            "WM",
            "WS"
        ],
        "markers": {
            "WN": {
                "pos": [
                    142.65,
                    138.57,
                    306.57
                ],
                "distanceFromTip": 281.3412
            },
            "WW": {
                "pos": [
                    96.34,
                    136.36,
                    257.37
                ],
                "distanceFromTip": 234.1736
            },
            "WE": {
                "pos": [
                    184.39,
                    138,
                    263.2
                ],
                "distanceFromTip": 243.98
            },
            "WM": {
                "pos": [
                    139.26,
                    136.25,
                    231.84
                ],
                "distanceFromTip": 206.5779
            },
            "WS": {
                "pos": [
                    135.94,
                    134.16,
                    161.84
                ],
                "distanceFromTip": 136.6144
            }
        },
        "offPlaneDist": 10.5,
        "algoSVD": 2
    },
    "ARFMode": [
        "LM"
    ]
}